scikit_ds/__init__.py
scikit_ds-0.0.1.dist-info/LICENSE
scikit_ds-0.0.1.dist-info/METADATA
scikit_ds-0.0.1.dist-info/WHEEL
scikit_ds-0.0.1.dist-info/entry_points.txt
scikit_ds-0.0.1.dist-info/top_level.txt
scikit_ds-0.0.1.dist-info/RECORD
