Metadata-Version: 2.1
Name: scikit-ds
Version: 0.0.1
Summary: Scientific toolkit for data science
Author: Cainã Max Couto da Silva
Author-email: cmcouto.silva@gmail.com
License: LICENSE
License-File: LICENSE
Requires-Dist: pandas >=1.0.0
